brightway_projects/__init__.py
brightway_projects/base_dir.py
brightway_projects/errors.py
brightway_projects/filesystem.py
brightway_projects/peewee.py
brightway_projects/projects.py
brightway_projects/testing.py
brightway_projects/version.py
brightway_projects-0.1.dev1.dist-info/LICENSE.txt
brightway_projects-0.1.dev1.dist-info/METADATA
brightway_projects-0.1.dev1.dist-info/WHEEL
brightway_projects-0.1.dev1.dist-info/top_level.txt
brightway_projects-0.1.dev1.dist-info/RECORD
