Metadata-Version: 2.1
Name: brightway-projects
Version: 0.1.dev1
Summary: Management of projects in the Brightway Life Cycle Asssessment framework
Home-page: https://github.com/brightway-lca/brightway_projects
Author: Chris Mutel
Author-email: cmutel@gmail.com
License: NewBSD 3-clause; LICENSE
Platform: UNKNOWN
Classifier: Development Status :: 3 - Alpha
Classifier: Intended Audience :: Science/Research
Classifier: License :: OSI Approved :: BSD License
Classifier: Operating System :: MacOS :: MacOS X
Classifier: Operating System :: Microsoft :: Windows
Classifier: Operating System :: POSIX
Classifier: Programming Language :: Python :: 3.7
Classifier: Topic :: Scientific/Engineering :: Information Analysis
Classifier: Topic :: Scientific/Engineering :: Mathematics
Requires-Dist: appdirs
Requires-Dist: peewee
